[
  {
    "caption": "Homer or Bust",
    "description": "Restoration of classical bust sculpture featuring comprehensive cleaning and structural repair.",
    "src": "assets/images/historic-preservation/homer-1.jpg"
  },
  {
    "caption": "Marble Piece",
    "description": "Complete marble restoration project involving crack repair and surface refinishing.",
    "src": "assets/images/historic-preservation/Marble-piece.jpg"
  },
  {
    "caption": "Office Restoration",
    "description": "Professional office space restoration focusing on period-appropriate decorative elements.",
    "src": "assets/images/historic-preservation/Office.jpg"
  },
  {
    "caption": "Old South Church",
    "description": "Historic church restoration project preserving original architectural details.",
    "src": "assets/images/historic-preservation/Old-South-Church.jpg"
  },
  {
    "caption": "Ceiling Fresco Restoration",
    "description": "Comprehensive ceiling fresco restoration including color matching and structural support.",
    "src": "assets/images/historic-preservation/Painting-Ceiling.jpg"
  },
  {
    "caption": "Wall Mural Restoration",
    "description": "Historic wall painting restoration with emphasis on color restoration and protective coating.",
    "src": "assets/images/historic-preservation/Painting-Wall.jpg"
  },
  {
    "caption": "Senate Presidential Wall",
    "description": "Senate presidential wall restoration preserving institutional heritage.",
    "src": "assets/images/historic-preservation/Senate-Pres-Wall.jpg"
  },
  {
    "caption": "St. Paul's Church",
    "description": "Religious art restoration project focusing on conservation and historical preservation.",
    "src": "assets/images/historic-preservation/StPauls.jpg"
  }
]
